beekeeper/guardrails/watsonx/__init__.py
beekeeper/guardrails/watsonx/base.py
beekeeper/guardrails/watsonx/supporting_classes/__init__.py
beekeeper/guardrails/watsonx/supporting_classes/enums.py
beekeeper_guardrails_watsonx-1.1.0.dist-info/METADATA
beekeeper_guardrails_watsonx-1.1.0.dist-info/WHEEL
beekeeper_guardrails_watsonx-1.1.0.dist-info/RECORD
