Metadata-Version: 2.4
Name: beekeeper-guardrails-watsonx
Version: 1.1.0
Summary: beekeeper guardrails watsonx extension
Author-email: Leonardo Furnielis <leonardofurnielis@outlook.com>
License: Apache-2.0
Requires-Python: <4.0,>=3.10
Requires-Dist: beekeeper-core<2.0.0,>=1.0.7
Requires-Dist: ibm-cloud-sdk-core<3.19.2,>=3.16.5
Provides-Extra: dev
Requires-Dist: ruff>=0.11.13; extra == 'dev'
